fastapi_profiler_rust-0.3.1.dist-info/METADATA
fastapi_profiler_rust-0.3.1.dist-info/WHEEL
rustcore/__init__.py
rustcore/rustcore.cp39-win_amd64.pyd
fastapi_profiler_rust-0.3.1.dist-info/RECORD
