Metadata-Version: 2.4
Name: fastapi-profiler-rust
Version: 0.3.1
Classifier: Programming Language :: Python :: 3
Classifier: Programming Language :: Python :: 3.8
Classifier: Programming Language :: Python :: 3.9
Classifier: Programming Language :: Python :: 3.10
Classifier: Programming Language :: Python :: 3.11
Classifier: Programming Language :: Python :: 3.12
Classifier: License :: OSI Approved :: MIT License
Classifier: Operating System :: OS Independent
Summary: Rust-powered statistics aggregator for FastAPI profiling
Author-email: Alexander Lind <al91liwo@gmail.com>
Requires-Python: >=3.8
